bookwyrm/__init__.py
bookwyrm/async_client.py
bookwyrm/cli.py
bookwyrm/client.py
bookwyrm/main.py
bookwyrm/models.py
bookwyrm/utils.py
bookwyrm-0.1.19.dist-info/METADATA
bookwyrm-0.1.19.dist-info/WHEEL
bookwyrm-0.1.19.dist-info/entry_points.txt
bookwyrm-0.1.19.dist-info/licenses/LICENSE
bookwyrm-0.1.19.dist-info/RECORD
