Metadata-Version: 2.4
Name: bookwyrm
Version: 0.1.19
Summary: A client library for BookWyrm
Project-URL: Homepage, https://bookwyrm.ai
Project-URL: Repository, https://github.com/scidonia/bookwyrm
Author-email: Gavin Mendel-Gleason <gavin@scidonia.ai>
License:                                  Apache License
License-File: LICENSE
Classifier: Development Status :: 3 - Alpha
Classifier: Intended Audience :: Developers
Classifier: Programming Language :: Python :: 3
Classifier: Programming Language :: Python :: 3.11
Classifier: Programming Language :: Python :: 3.12
Requires-Python: >=3.11
Requires-Dist: httpx-sse>=0.4.0
Requires-Dist: httpx>=0.24.0
Requires-Dist: pydantic>=2.0.0
Requires-Dist: requests>=2.25.0
Requires-Dist: rich>=13.0.0
Requires-Dist: sseclient-py>=1.7.0
Requires-Dist: typer>=0.19.2
Provides-Extra: dev
Requires-Dist: black>=22.0; extra == 'dev'
Requires-Dist: click>=8.0.0; extra == 'dev'
Requires-Dist: flake8>=4.0; extra == 'dev'
Requires-Dist: mkdocs-click>=0.9.0; extra == 'dev'
Requires-Dist: mkdocs-typer>=0.0.3; extra == 'dev'
Requires-Dist: mypy>=0.900; extra == 'dev'
Requires-Dist: pytest-asyncio>=0.21.0; extra == 'dev'
Requires-Dist: pytest>=6.0; extra == 'dev'
